dkh_asteroid/__init__.py
dkh_asteroid-1.0.2.dist-info/LICENSE
dkh_asteroid-1.0.2.dist-info/METADATA
dkh_asteroid-1.0.2.dist-info/WHEEL
dkh_asteroid-1.0.2.dist-info/top_level.txt
dkh_asteroid-1.0.2.dist-info/RECORD
