Metadata-Version: 2.1
Name: dkh-asteroid
Version: 1.0.2
Summary: Тестовый пакет
Home-page: https://github.com/dkh-gh/asteroid1-game
Author: Дмитрий Холостов
Author-email: dkh@ro.ru
License: UNKNOWN
Platform: UNKNOWN
Classifier: Programming Language :: Python :: 3
Classifier: License :: OSI Approved :: MIT License
Classifier: Operating System :: OS Independent
Requires-Python: >=3.6
